{
  "generated_at": "2026-05-22 07:44:43",
  "news": [
    {
      "title": "CODA: Rewriting Transformer Blocks as GEMM-Epilogue Programs",
      "url": "https://arxiv.org/abs/2605.19269",
      "source": "Hacker News",
      "time": "2026-05-22 04:54",
      "score": 47,
      "comments": 3
    },
    {
      "title": "Project Hail Mary – Stellar Navigation Chart",
      "url": "https://valhovey.github.io/gaia-mary/",
      "source": "Hacker News",
      "time": "2026-05-21 16:23",
      "score": 828,
      "comments": 183
    }
  ]
}