{
  "generated_at": "2026-04-15 20:50:35",
  "news": [
    {
      "title": "Fix monitor that goes black, off or blinks due to static electricity in chair",
      "url": "https://aalonso.dev/blog/2023/how-to-fix-monitor-that-goes-black-off-due-to-static-electricity-in-chair/",
      "source": "Hacker News",
      "time": "2026-04-12 10:27",
      "score": 78,
      "comments": 39
    },
    {
      "title": "AI-assisted cognition endangers human development",
      "url": "https://heidenstedt.org/posts/2026/ai-assisted-cognition-endangers-human-development/",
      "source": "Hacker News",
      "time": "2026-04-15 18:16",
      "score": 204,
      "comments": 129
    }
  ]
}